<annotation>
	<folder>my_file</folder>
	<filename>vid_4_13860.jpg</filename>
	<path>C:\Users\sosum\Desktop\Amalitech\Vehicle-detection-model\my_file\vid_4_13860.jpg</path>
	<source>
		<database>Unknown</database>
	</source>
	<size>
		<width>676</width>
		<height>380</height>
		<depth>3</depth>
	</size>
	<segmented>0</segmented>
	<object>
		<name>car</name>
		<pose>Unspecified</pose>
		<truncated>0</truncated>
		<difficult>0</difficult>
		<bndbox>
			<xmin>13</xmin>
			<ymin>196</ymin>
			<xmax>89</xmax>
			<ymax>236</ymax>
		</bndbox>
	</object>
	<object>
		<name>car</name>
		<pose>Unspecified</pose>
		<truncated>0</truncated>
		<difficult>0</difficult>
		<bndbox>
			<xmin>432</xmin>
			<ymin>193</ymin>
			<xmax>598</xmax>
			<ymax>252</ymax>
		</bndbox>
	</object>
	<object>
		<name>car</name>
		<pose>Unspecified</pose>
		<truncated>0</truncated>
		<difficult>0</difficult>
		<bndbox>
			<xmin>612</xmin>
			<ymin>178</ymin>
			<xmax>673</xmax>
			<ymax>219</ymax>
		</bndbox>
	</object>
</annotation>
